CHANGELOG.rst
DESIGN.txt
LICENSE.txt
MANIFEST.in
README.rst
TODO.txt
VERSION.txt
requirements.txt
setup.cfg
setup.py
test-requirements.txt
pyramid_scheduler/__init__.py
pyramid_scheduler/api.py
pyramid_scheduler/broker.py
pyramid_scheduler/pscheduler.py
pyramid_scheduler/scheduler.py
pyramid_scheduler/test.py
pyramid_scheduler/util.py
pyramid_scheduler.egg-info/PKG-INFO
pyramid_scheduler.egg-info/SOURCES.txt
pyramid_scheduler.egg-info/dependency_links.txt
pyramid_scheduler.egg-info/entry_points.txt
pyramid_scheduler.egg-info/requires.txt
pyramid_scheduler.egg-info/top_level.txt
pyramid_scheduler.egg-info/zip-safe